[
  {
    "id": 1,
    "title": "Замена масла ДВС с фильтром",
    "types": 1
  },
  {
    "id": 2,
    "title": "Замена воздушного фильтра ДВС",
    "types": 1
  },
  {
    "id": 3,
    "title": "Замена свечей зажигания",
    "types": 1
  },
  {
    "id": 4,
    "title": "Замена катушки зажигания",
    "types": 1
  },
  {
    "id": 5,
    "title": "Замена водяного насоса (помпа)",
    "types": 1
  },
  {
    "id": 6,
    "title": "Замена термостата",
    "types": 1
  },
  {
    "id": 7,
    "title": "Замена топливного насоса",
    "types": 1
  },
  {
    "id": 8,
    "title": "Замена сцепления (в сборе)",
    "types": 1
  },
  {
    "id": 9,
    "title": "Замена ремня ГРМ с роликами",
    "types": 1
  },
  {
    "id": 10,
    "title": "Замена масла КПП",
    "types": 1
  }
]